lockserver_client.py
lockserver_client-0.1.0.dist-info/METADATA
lockserver_client-0.1.0.dist-info/WHEEL
lockserver_client-0.1.0.dist-info/top_level.txt
lockserver_client-0.1.0.dist-info/RECORD
