Metadata-Version: 2.4
Name: lockserver-client
Version: 0.1.0
Summary: Python client SDK for lockserver (distributed lock server)
Home-page: https://github.com/benliao/lockserver
Author: Ben Liao
Author-email: abenliao@gmail.com
License: MIT
Keywords: distributed lock server client sdk python
Classifier: Programming Language :: Python :: 3
Classifier: License :: OSI Approved :: MIT License
Classifier: Operating System :: OS Independent
Requires-Dist: requests
Dynamic: author
Dynamic: author-email
Dynamic: classifier
Dynamic: home-page
Dynamic: keywords
Dynamic: license
Dynamic: requires-dist
Dynamic: summary
